[
    {
      "_id": "633e7a717c0c86b515f4cf33",
      "index": 0,
      "guid": "8dabe71a-7d1f-4fd5-99ec-705ac18efa0e",
      "isActive": false,
      "balance": "$3,855.69",
      "picture": "https://images.unsplash.com/photo-1517836357463-d25dfeac3438?ixlib=rb-1.2.1&ixid=MnwxMjA3fDB8MHxzZWFyY2h8NHx8Z3ltfGVufDB8fDB8fA%3D%3D&auto=format&fit=crop&w=500&q=60",
      "age": 24,
      "eyeColor": "blue",
      "name": "Dumble",
      "gender": "male",
      "company": "DEVILTOE",
      "email": "fultonmadden@deviltoe.com",
      "phone": "+1 (981) 474-2007",
      "address": "577 Mill Road, Cotopaxi, Maine, 6252",
      "about": "Ipsum anim exercitation ea dolor do id. Deserunt qui non veniam occaecat. Excepteur commodo est occaecat consequat culpa proident elit ipsum quis. Duis exercitation ut exercitation eu quis consequat incididunt do. Aute pariatur quis eu nostrud in excepteur.\r\n"
    },
    {
      "_id": "633e7a71b5c2b834f64887cd",
      "index": 1,
      "guid": "cbb52524-3ed4-428d-9535-3314c320fbf2",
      "isActive": true,
      "balance": "$1,197.28",
      "picture": "https://images.unsplash.com/photo-1581009146145-b5ef050c2e1e?ixlib=rb-1.2.1&ixid=MnwxMjA3fDB8MHxzZWFyY2h8MTB8fGd5bXxlbnwwfHwwfHw%3D&auto=format&fit=crop&w=500&q=60",
      "age": 21,
      "eyeColor": "blue",
      "name": "Hand Stick",
      "gender": "male",
      "company": "RADIANTIX",
      "email": "hardingarrison@radiantix.com",
      "phone": "+1 (973) 440-3651",
      "address": "347 Colonial Road, Bellfountain, Arizona, 4321",
      "about": "Deserunt magna aute nostrud ut labore nostrud duis reprehenderit. Ad ea in deserunt in do. Elit aute mollit do sint eiusmod nulla culpa. Duis in nostrud deserunt deserunt amet.\r\n"
    },
    {
      "_id": "633e7a71bf284629f9e0d404",
      "index": 2,
      "guid": "c00d1635-57c7-4f6f-967b-e93d7e4bdcdd",
      "isActive": false,
      "balance": "$2,697.28",
      "picture": "https://plus.unsplash.com/premium_photo-1661265884304-258ed1637407?ixlib=rb-1.2.1&ixid=MnwxMjA3fDB8MHxzZWFyY2h8MTl8fGd5bXxlbnwwfHwwfHw%3D&auto=format&fit=crop&w=500&q=60",
      "age": 39,
      "eyeColor": "brown",
      "name": "Power Ball",
      "gender": "male",
      "company": "COSMOSIS",
      "email": "brocklara@cosmosis.com",
      "phone": "+1 (860) 422-2982",
      "address": "949 Hamilton Walk, Cashtown, Nevada, 4850",
      "about": "Ipsum ex anim nisi in enim duis nostrud qui. Quis eu dolore fugiat ullamco duis Lorem deserunt Lorem. Laborum excepteur quis aliqua qui non. Laborum nisi qui sunt id sit culpa nulla duis est elit et adipisicing reprehenderit.\r\n"
    },
    {
      "_id": "633e7a711eb6b641d6cba973",
      "index": 3,
      "guid": "59c2532e-6c83-469e-a923-9dd850cd59aa",
      "isActive": true,
      "balance": "$3,179.21",
      "picture": " https://plus.unsplash.com/premium_photo-1663050861006-5249d781336f?ixlib=rb-1.2.1&ixid=MnwxMjA3fDB8MHxzZWFyY2h8MTN8fGd5bXxlbnwwfHwwfHw%3D&auto=format&fit=crop&w=500&q=60",
      "age": 25,
      "eyeColor": "blue",
      "name": "TreadMeal",
      "gender": "female",
      "company": "ZENSURE",
      "email": "miriampowers@zensure.com",
      "phone": "+1 (916) 581-2373",
      "address": "877 Bancroft Place, Coinjock, California, 7426",
      "about": "Commodo do minim cillum nostrud laborum sunt ea ut ea tempor amet anim. Et sint nulla pariatur reprehenderit dolor quis est pariatur esse eu aliqua fugiat ut tempor. Labore labore mollit sunt nisi qui dolore. Quis fugiat do proident ipsum non ad Lorem nostrud cupidatat do velit dolore aliqua irure. Occaecat adipisicing et consectetur reprehenderit exercitation occaecat aliqua velit. Tempor laborum ut sint irure.\r\n"
    },
    {
      "_id": "633e7a71110da92bf9c03eeb",
      "index": 4,
      "guid": "635744e2-6b4d-4643-9641-637fed805f7d",
      "isActive": true,
      "balance": "$1,301.42",
      "picture": "https://images.unsplash.com/photo-1518611012118-696072aa579a?ixlib=rb-1.2.1&ixid=MnwxMjA3fDB8MHxzZWFyY2h8MzN8fGd5bXxlbnwwfHwwfHw%3D&auto=format&fit=crop&w=500&q=60",
      "age": 40,
      "eyeColor": "blue",
      "name": "Dumble",
      "gender": "male",
      "company": "PROXSOFT",
      "email": "gibbsbriggs@proxsoft.com",
      "phone": "+1 (994) 522-2662",
      "address": "703 Roosevelt Place, Rossmore, Pennsylvania, 8126",
      "about": "Dolor nisi dolore irure adipisicing commodo dolore. Nulla qui do do dolor fugiat dolore enim in sit ea nulla incididunt do. Nisi laboris irure consequat reprehenderit sint aliqua est proident aute.\r\n"
    },
    {
      "_id": "633e7a71c8d10a6b2036f548",
      "index": 5,
      "guid": "f2eeb744-6afd-45d1-955a-f56ce43c5843",
      "isActive": true,
      "balance": "$3,337.58",
      "picture": "https://images.unsplash.com/photo-1546483875-ad9014c88eba?ixlib=rb-1.2.1&ixid=MnwxMjA3fDB8MHxzZWFyY2h8Mjh8fGd5bXxlbnwwfHwwfHw%3D&auto=format&fit=crop&w=500&q=60",
      "age": 35,
      "eyeColor": "brown",
      "name": "Hand Stick",
      "gender": "male",
      "company": "ENDICIL",
      "email": "johnsonbarker@endicil.com",
      "phone": "+1 (881) 427-2512",
      "address": "457 Chapel Street, Utting, Missouri, 2623",
      "about": "Et eiusmod excepteur aliquip nisi anim cupidatat. Est consectetur deserunt esse commodo do ipsum occaecat consequat aliquip tempor commodo eu proident. Ullamco qui in proident excepteur eu esse Lorem minim fugiat consequat. Minim est sint amet Lorem commodo incididunt labore cillum labore eu dolor quis.\r\n"
    }
  ]